{
  "Ads": [
    {
      "select_main_ads": "FACEBOOK",
      "select_backup_ads":"ADMOB",
      "main_ads_banner": "",
      "main_ads_intertitial":"",
      "backup_ads_banner":"",
      "backup_ads_intertitial":"",
      "interval_intertitial": 2,
      "initialize_sdk":"",
      "initialize_sdk_backup_ads":"",
      "high_paying_keyword_1": "",
      "high_paying_keyword_2": "",
      "high_paying_keyword_3": "",
      "high_paying_keyword_4": "",
      "high_paying_keyword_5": "",
      "status_app": "0",
      "link_redirect": "https://"
    }
  ],
  "More":
  [
    
  ],
  "Skin": [
    {
      "id": 1,
      "name_skin": "Pico Skin",
      "install_skin": "https://raw.githubusercontent.com/Selalubersamanya7789/signedobson/main/p1cov5/png/skin1.png"
    },
    {
      "id": 2,
      "name_skin": "Pico Skin",
      "install_skin": "https://raw.githubusercontent.com/Selalubersamanya7789/signedobson/main/p1cov5/png/skin2.png"
    },
    {
      "id": 3,
      "name_skin": "Pico Skin",
      "install_skin": "https://raw.githubusercontent.com/Selalubersamanya7789/signedobson/main/p1cov5/png/skin3.png"
    },
    {
      "id": 4,
      "name_skin": "Pico Skin",
      "install_skin": "https://raw.githubusercontent.com/Selalubersamanya7789/signedobson/main/p1cov5/png/skin4.png"
    },
    {
      "id": 5,
      "name_skin": "Pico Skin",
      "install_skin": "https://raw.githubusercontent.com/Selalubersamanya7789/signedobson/main/p1cov5/png/skin5.png"
    },
    {
      "id": 6,
      "name_skin": "Pico Skin",
      "install_skin": "https://raw.githubusercontent.com/Selalubersamanya7789/signedobson/main/p1cov5/png/skin6.png"
    },
    {
      "id": 7,
      "name_skin": "Pico Skin",
      "install_skin": "https://raw.githubusercontent.com/Selalubersamanya7789/signedobson/main/p1cov5/png/skin7.png"
    },
    {
      "id": 8,
      "name_skin": "Pico Skin",
      "install_skin": "https://raw.githubusercontent.com/Selalubersamanya7789/signedobson/main/p1cov5/png/skin8.png"
    },
    {
      "id": 9,
      "name_skin": "Pico Skin",
      "install_skin": "https://raw.githubusercontent.com/Selalubersamanya7789/signedobson/main/p1cov5/png/skin9.png"
    },
    {
      "id": 10,
      "name_skin": "Pico Skin",
      "install_skin": "https://raw.githubusercontent.com/Selalubersamanya7789/signedobson/main/p1cov5/png/skin10.png"
    },
    {
      "id": 11,
      "name_skin": "Pico Skin",
      "install_skin": "https://raw.githubusercontent.com/Selalubersamanya7789/signedobson/main/p1cov5/png/skin11.png"
    },
    {
      "id": 12,
      "name_skin": "Pico Skin",
      "install_skin": "https://raw.githubusercontent.com/Selalubersamanya7789/signedobson/main/p1cov5/png/skin12.png"
    },
    {
      "id": 13,
      "name_skin": "Pico Skin",
      "install_skin": "https://raw.githubusercontent.com/Selalubersamanya7789/signedobson/main/p1cov5/png/skin13.png"
    },
    {
      "id": 14,
      "name_skin": "Pico Skin",
      "install_skin": "https://raw.githubusercontent.com/Selalubersamanya7789/signedobson/main/p1cov5/png/skin14.png"
    },
    {
      "id": 15,
      "name_skin": "Pico Skin",
      "install_skin": "https://raw.githubusercontent.com/Selalubersamanya7789/signedobson/main/p1cov5/png/skin15.png"
    },
    {
      "id": 16,
      "name_skin": "Pico Skin",
      "install_skin": "https://raw.githubusercontent.com/Selalubersamanya7789/signedobson/main/p1cov5/png/skin16.png"
    },
    {
      "id": 17,
      "name_skin": "Pico Skin",
      "install_skin": "https://raw.githubusercontent.com/Selalubersamanya7789/signedobson/main/p1cov5/png/skin17.png"
    },
    {
      "id": 18,
      "name_skin": "Pico Skin",
      "install_skin": "https://raw.githubusercontent.com/Selalubersamanya7789/signedobson/main/p1cov5/png/skin18.png"
    },
    {
      "id": 19,
      "name_skin": "Pico Skin",
      "install_skin": "https://raw.githubusercontent.com/Selalubersamanya7789/signedobson/main/p1cov5/png/skin19.png"
    },
    {
      "id": 20,
      "name_skin": "Pico Skin",
      "install_skin": "https://raw.githubusercontent.com/Selalubersamanya7789/signedobson/main/p1cov5/png/skin20.png"
    },
    {
      "id": 21,
      "name_skin": "Pico Skin",
      "install_skin": "https://raw.githubusercontent.com/Selalubersamanya7789/signedobson/main/p1cov5/png/skin21.png"
    },
    {
      "id": 22,
      "name_skin": "Pico Skin",
      "install_skin": "https://raw.githubusercontent.com/Selalubersamanya7789/signedobson/main/p1cov5/png/skin22.png"
    },
    {
      "id": 23,
      "name_skin": "Pico Skin",
      "install_skin": "https://raw.githubusercontent.com/Selalubersamanya7789/signedobson/main/p1cov5/png/skin23.png"
    },
    {
      "id": 24,
      "name_skin": "Pico Skin",
      "install_skin": "https://raw.githubusercontent.com/Selalubersamanya7789/signedobson/main/p1cov5/png/skin24.png"
    },
    {
      "id": 25,
      "name_skin": "Pico Skin",
      "install_skin": "https://raw.githubusercontent.com/Selalubersamanya7789/signedobson/main/p1cov5/png/skin25.png"
    },
    {
      "id": 26,
      "name_skin": "Pico Skin",
      "install_skin": "https://raw.githubusercontent.com/Selalubersamanya7789/signedobson/main/p1cov5/png/skin26.png"
    },
    {
      "id": 27,
      "name_skin": "Pico Skin",
      "install_skin": "https://raw.githubusercontent.com/Selalubersamanya7789/signedobson/main/p1cov5/png/skin27.png"
    },
    {
      "id": 28,
      "name_skin": "Pico Skin",
      "install_skin": "https://raw.githubusercontent.com/Selalubersamanya7789/signedobson/main/p1cov5/png/skin28.png"
    },
    {
      "id": 29,
      "name_skin": "Pico Skin",
      "install_skin": "https://raw.githubusercontent.com/Selalubersamanya7789/signedobson/main/p1cov5/png/skin29.png"
    },
    {
      "id": 30,
      "name_skin": "Pico Skin",
      "install_skin": "https://raw.githubusercontent.com/Selalubersamanya7789/signedobson/main/p1cov5/png/skin30.png"
    },
  {
      "id": 31,
      "name_skin": "Pico Skin",
      "install_skin": "https://raw.githubusercontent.com/Selalubersamanya7789/signedobson/main/p1cov5/png/skin31.png"
    },
    {
      "id": 32,
      "name_skin": "Pico Skin",
      "install_skin": "https://raw.githubusercontent.com/Selalubersamanya7789/signedobson/main/p1cov5/png/skin32.png"
    },
    {
      "id": 33,
      "name_skin": "Pico Skin",
      "install_skin": "https://raw.githubusercontent.com/Selalubersamanya7789/signedobson/main/p1cov5/png/skin33.png"
    },
    {
      "id": 34,
      "name_skin": "Pico Skin",
      "install_skin": "https://raw.githubusercontent.com/Selalubersamanya7789/signedobson/main/p1cov5/png/skin34.png"
    },
    {
      "id": 35,
      "name_skin": "Pico Skin",
      "install_skin": "https://raw.githubusercontent.com/Selalubersamanya7789/signedobson/main/p1cov5/png/skin35.png"
    },
    {
      "id": 36,
      "name_skin": "Pico Skin",
      "install_skin": "https://raw.githubusercontent.com/Selalubersamanya7789/signedobson/main/p1cov5/png/skin36.png"
    },
    {
      "id": 37,
      "name_skin": "Pico Skin",
      "install_skin": "https://raw.githubusercontent.com/Selalubersamanya7789/signedobson/main/p1cov5/png/skin37.png"
    },
    {
      "id": 38,
      "name_skin": "Pico Skin",
      "install_skin": "https://raw.githubusercontent.com/Selalubersamanya7789/signedobson/main/p1cov5/png/skin38.png"
    },
    {
      "id": 39,
      "name_skin": "Pico Skin",
      "install_skin": "https://raw.githubusercontent.com/Selalubersamanya7789/signedobson/main/p1cov5/png/skin39.png"
    },
    {
      "id": 40,
      "name_skin": "Pico Skin",
      "install_skin": "https://raw.githubusercontent.com/Selalubersamanya7789/signedobson/main/p1cov5/png/skin40.png"
    },
  {
      "id": 41,
      "name_skin": "Pico Skin",
      "install_skin": "https://raw.githubusercontent.com/Selalubersamanya7789/signedobson/main/p1cov5/png/skin41.png"
    },
    {
      "id": 42,
      "name_skin": "Pico Skin",
      "install_skin": "https://raw.githubusercontent.com/Selalubersamanya7789/signedobson/main/p1cov5/png/skin42.png"
    },
    {
      "id": 43,
      "name_skin": "Pico Skin",
      "install_skin": "https://raw.githubusercontent.com/Selalubersamanya7789/signedobson/main/p1cov5/png/skin43.png"
    },
    {
      "id": 44,
      "name_skin": "Pico Skin",
      "install_skin": "https://raw.githubusercontent.com/Selalubersamanya7789/signedobson/main/p1cov5/png/skin44.png"
    },
    {
      "id": 45,
      "name_skin": "Pico Skin",
      "install_skin": "https://raw.githubusercontent.com/Selalubersamanya7789/signedobson/main/p1cov5/png/skin45.png"
    },
    {
      "id": 46,
      "name_skin": "Pico Skin",
      "install_skin": "https://raw.githubusercontent.com/Selalubersamanya7789/signedobson/main/p1cov5/png/skin46.png"
    },
    {
      "id": 47,
      "name_skin": "Pico Skin",
      "install_skin": "https://raw.githubusercontent.com/Selalubersamanya7789/signedobson/main/p1cov5/png/skin47.png"
    },
    {
      "id": 48,
      "name_skin": "Pico Skin",
      "install_skin": "https://raw.githubusercontent.com/Selalubersamanya7789/signedobson/main/p1cov5/png/skin48.png"
    },
    {
      "id": 49,
      "name_skin": "Pico Skin",
      "install_skin": "https://raw.githubusercontent.com/Selalubersamanya7789/signedobson/main/p1cov5/png/skin49.png"
    },
    {
      "id": 50,
      "name_skin": "Pico Skin",
      "install_skin": "https://raw.githubusercontent.com/Selalubersamanya7789/signedobson/main/p1cov5/png/skin50.png"
    },
    {
      "id": 51,
      "name_skin": "Pico Skin",
      "install_skin": "https://raw.githubusercontent.com/Selalubersamanya7789/signedobson/main/p1cov5/png/skin51.png"
    },
    {
      "id": 52,
      "name_skin": "Pico Skin",
      "install_skin": "https://raw.githubusercontent.com/Selalubersamanya7789/signedobson/main/p1cov5/png/skin52.png"
    },
    {
      "id": 53,
      "name_skin": "Pico Skin",
      "install_skin": "https://raw.githubusercontent.com/Selalubersamanya7789/signedobson/main/p1cov5/png/skin53.png"
    },
    {
      "id": 54,
      "name_skin": "Pico Skin",
      "install_skin": "https://raw.githubusercontent.com/Selalubersamanya7789/signedobson/main/p1cov5/png/skin54.png"
    },
    {
      "id": 55,
      "name_skin": "Pico Skin",
      "install_skin": "https://raw.githubusercontent.com/Selalubersamanya7789/signedobson/main/p1cov5/png/skin55.png"
    },
    {
      "id": 56,
      "name_skin": "Pico Skin",
      "install_skin": "https://raw.githubusercontent.com/Selalubersamanya7789/signedobson/main/p1cov5/png/skin56.png"
    },
    {
      "id": 57,
      "name_skin": "Pico Skin",
      "install_skin": "https://raw.githubusercontent.com/Selalubersamanya7789/signedobson/main/p1cov5/png/skin57.png"
    },
    {
      "id": 58,
      "name_skin": "Pico Skin",
      "install_skin": "https://raw.githubusercontent.com/Selalubersamanya7789/signedobson/main/p1cov5/png/skin58.png"
    },
    {
      "id": 59,
      "name_skin": "Pico Skin",
      "install_skin": "https://raw.githubusercontent.com/Selalubersamanya7789/signedobson/main/p1cov5/png/skin59.png"
    },
    {
      "id": 60,
      "name_skin": "Pico Skin",
      "install_skin": "https://raw.githubusercontent.com/Selalubersamanya7789/signedobson/main/p1cov5/png/skin60.png"
    },
    {
      "id": 61,
      "name_skin": "Pico Skin",
      "install_skin": "https://raw.githubusercontent.com/Selalubersamanya7789/signedobson/main/p1cov5/png/skin61.png"
    },
    {
      "id": 62,
      "name_skin": "Pico Skin",
      "install_skin": "https://raw.githubusercontent.com/Selalubersamanya7789/signedobson/main/p1cov5/png/skin62.png"
    },
    {
      "id": 63,
      "name_skin": "Pico Skin",
      "install_skin": "https://raw.githubusercontent.com/Selalubersamanya7789/signedobson/main/p1cov5/png/skin63.png"
    },
    {
      "id": 64,
      "name_skin": "Pico Skin",
      "install_skin": "https://raw.githubusercontent.com/Selalubersamanya7789/signedobson/main/p1cov5/png/skin64.png"
    },
    {
      "id": 65,
      "name_skin": "Pico Skin",
      "install_skin": "https://raw.githubusercontent.com/Selalubersamanya7789/signedobson/main/p1cov5/png/skin65.png"
    },
    {
      "id": 66,
      "name_skin": "Pico Skin",
      "install_skin": "https://raw.githubusercontent.com/Selalubersamanya7789/signedobson/main/p1cov5/png/skin66.png"
    },
    {
      "id": 67,
      "name_skin": "Pico Skin",
      "install_skin": "https://raw.githubusercontent.com/Selalubersamanya7789/signedobson/main/p1cov5/png/skin67.png"
    },
    {
      "id": 68,
      "name_skin": "Pico Skin",
      "install_skin": "https://raw.githubusercontent.com/Selalubersamanya7789/signedobson/main/p1cov5/png/skin68.png"
    },
    {
      "id": 69,
      "name_skin": "Pico Skin",
      "install_skin": "https://raw.githubusercontent.com/Selalubersamanya7789/signedobson/main/p1cov5/png/skin69.png"
    },
    {
      "id": 70,
      "name_skin": "Pico Skin",
      "install_skin": "https://raw.githubusercontent.com/Selalubersamanya7789/signedobson/main/p1cov5/png/skin70.png"
    },
    {
      "id": 71,
      "name_skin": "Pico Skin",
      "install_skin": "https://raw.githubusercontent.com/Selalubersamanya7789/signedobson/main/p1cov5/png/skin71.png"
    },
    {
      "id": 72,
      "name_skin": "Pico Skin",
      "install_skin": "https://raw.githubusercontent.com/Selalubersamanya7789/signedobson/main/p1cov5/png/skin72.png"
    },
    {
      "id": 73,
      "name_skin": "Pico Skin",
      "install_skin": "https://raw.githubusercontent.com/Selalubersamanya7789/signedobson/main/p1cov5/png/skin73.png"
    },
    {
      "id": 74,
      "name_skin": "Pico Skin",
      "install_skin": "https://raw.githubusercontent.com/Selalubersamanya7789/signedobson/main/p1cov5/png/skin74.png"
    },
    {
      "id": 75,
      "name_skin": "Pico Skin",
      "install_skin": "https://raw.githubusercontent.com/Selalubersamanya7789/signedobson/main/p1cov5/png/skin75.png"
    },
    {
      "id": 76,
      "name_skin": "Pico Skin",
      "install_skin": "https://raw.githubusercontent.com/Selalubersamanya7789/signedobson/main/p1cov5/png/skin76.png"
    },
    {
      "id": 77,
      "name_skin": "Pico Skin",
      "install_skin": "https://raw.githubusercontent.com/Selalubersamanya7789/signedobson/main/p1cov5/png/skin77.png"
    },
    {
      "id": 78,
      "name_skin": "Pico Skin",
      "install_skin": "https://raw.githubusercontent.com/Selalubersamanya7789/signedobson/main/p1cov5/png/skin78.png"
    },
    {
      "id": 79,
      "name_skin": "Pico Skin",
      "install_skin": "https://raw.githubusercontent.com/Selalubersamanya7789/signedobson/main/p1cov5/png/skin79.png"
    },
    {
      "id": 80,
      "name_skin": "Pico Skin",
      "install_skin": "https://raw.githubusercontent.com/Selalubersamanya7789/signedobson/main/p1cov5/png/skin80.png"
    },
    {
      "id": 81,
      "name_skin": "Pico Skin",
      "install_skin": "https://raw.githubusercontent.com/Selalubersamanya7789/signedobson/main/p1cov5/png/skin81.png"
    },
    {
      "id": 82,
      "name_skin": "Pico Skin",
      "install_skin": "https://raw.githubusercontent.com/Selalubersamanya7789/signedobson/main/p1cov5/png/skin82.png"
    },
    {
      "id": 83,
      "name_skin": "Pico Skin",
      "install_skin": "https://raw.githubusercontent.com/Selalubersamanya7789/signedobson/main/p1cov5/png/skin83.png"
    },
    {
      "id": 84,
      "name_skin": "Pico Skin",
      "install_skin": "https://raw.githubusercontent.com/Selalubersamanya7789/signedobson/main/p1cov5/png/skin84.png"
    },
    {
      "id": 85,
      "name_skin": "Pico Skin",
      "install_skin": "https://raw.githubusercontent.com/Selalubersamanya7789/signedobson/main/p1cov5/png/skin85.png"
    },
    {
      "id": 86,
      "name_skin": "Pico Skin",
      "install_skin": "https://raw.githubusercontent.com/Selalubersamanya7789/signedobson/main/p1cov5/png/skin86.png"
    },
    {
      "id": 87,
      "name_skin": "Pico Skin",
      "install_skin": "https://raw.githubusercontent.com/Selalubersamanya7789/signedobson/main/p1cov5/png/skin87.png"
    },
    {
      "id": 88,
      "name_skin": "Pico Skin",
      "install_skin": "https://raw.githubusercontent.com/Selalubersamanya7789/signedobson/main/p1cov5/png/skin88.png"
    },
    {
      "id": 89,
      "name_skin": "Pico Skin",
      "install_skin": "https://raw.githubusercontent.com/Selalubersamanya7789/signedobson/main/p1cov5/png/skin89.png"
    },
    {
      "id": 90,
      "name_skin": "Pico Skin",
      "install_skin": "https://raw.githubusercontent.com/Selalubersamanya7789/signedobson/main/p1cov5/png/skin90.png"
    },
    {
      "id": 91,
      "name_skin": "Pico Skin",
      "install_skin": "https://raw.githubusercontent.com/Selalubersamanya7789/signedobson/main/p1cov5/png/skin91.png"
    },
    {
      "id": 92,
      "name_skin": "Pico Skin",
      "install_skin": "https://raw.githubusercontent.com/Selalubersamanya7789/signedobson/main/p1cov5/png/skin92.png"
    },
    {
      "id": 93,
      "name_skin": "Pico Skin",
      "install_skin": "https://raw.githubusercontent.com/Selalubersamanya7789/signedobson/main/p1cov5/png/skin93.png"
    },
    {
      "id": 94,
      "name_skin": "Pico Skin",
      "install_skin": "https://raw.githubusercontent.com/Selalubersamanya7789/signedobson/main/p1cov5/png/skin94.png"
    },
    {
      "id": 95,
      "name_skin": "Pico Skin",
      "install_skin": "https://raw.githubusercontent.com/Selalubersamanya7789/signedobson/main/p1cov5/png/skin95.png"
    },
    {
      "id": 96,
      "name_skin": "Pico Skin",
      "install_skin": "https://raw.githubusercontent.com/Selalubersamanya7789/signedobson/main/p1cov5/png/skin96.png"
    },
    {
      "id": 97,
      "name_skin": "Pico Skin",
      "install_skin": "https://raw.githubusercontent.com/Selalubersamanya7789/signedobson/main/p1cov5/png/skin97.png"
    },
    {
      "id": 98,
      "name_skin": "Pico Skin",
      "install_skin": "https://raw.githubusercontent.com/Selalubersamanya7789/signedobson/main/p1cov5/png/skin98.png"
    },
    {
      "id": 99,
      "name_skin": "Pico Skin",
      "install_skin": "https://raw.githubusercontent.com/Selalubersamanya7789/signedobson/main/p1cov5/png/skin99.png"
    },
    {
      "id": 100,
      "name_skin": "Pico Skin",
      "install_skin": "https://raw.githubusercontent.com/Selalubersamanya7789/signedobson/main/p1cov5/png/skin100.png"
    },
    {
      "id": 101,
      "name_skin": "Pico Skin",
      "install_skin": "https://raw.githubusercontent.com/Selalubersamanya7789/signedobson/main/p1cov5/png/skin101.png"
    },
    {
      "id": 102,
      "name_skin": "Pico Skin",
      "install_skin": "https://raw.githubusercontent.com/Selalubersamanya7789/signedobson/main/p1cov5/png/skin102.png"
    },
    {
      "id": 103,
      "name_skin": "Pico Skin",
      "install_skin": "https://raw.githubusercontent.com/Selalubersamanya7789/signedobson/main/p1cov5/png/skin103.png"
    },
    {
      "id": 104,
      "name_skin": "Pico Skin",
      "install_skin": "https://raw.githubusercontent.com/Selalubersamanya7789/signedobson/main/p1cov5/png/skin104.png"
    },
    {
      "id": 105,
      "name_skin": "Pico Skin",
      "install_skin": "https://raw.githubusercontent.com/Selalubersamanya7789/signedobson/main/p1cov5/png/skin105.png"
    },
    {
      "id": 106,
      "name_skin": "Pico Skin",
      "install_skin": "https://raw.githubusercontent.com/Selalubersamanya7789/signedobson/main/p1cov5/png/skin106.png"
    },
    {
      "id": 107,
      "name_skin": "Pico Skin",
      "install_skin": "https://raw.githubusercontent.com/Selalubersamanya7789/signedobson/main/p1cov5/png/skin107.png"
    },
    {
      "id": 108,
      "name_skin": "Pico Skin",
      "install_skin": "https://raw.githubusercontent.com/Selalubersamanya7789/signedobson/main/p1cov5/png/skin108.png"
    },
    {
      "id": 109,
      "name_skin": "Pico Skin",
      "install_skin": "https://raw.githubusercontent.com/Selalubersamanya7789/signedobson/main/p1cov5/png/skin109.png"
    },
    {
      "id": 110,
      "name_skin": "Pico Skin",
      "install_skin": "https://raw.githubusercontent.com/Selalubersamanya7789/signedobson/main/p1cov5/png/skin110.png"
    },
    {
      "id": 111,
      "name_skin": "Pico Skin",
      "install_skin": "https://raw.githubusercontent.com/Selalubersamanya7789/signedobson/main/p1cov5/png/skin111.png"
    },
    {
      "id": 112,
      "name_skin": "Pico Skin",
      "install_skin": "https://raw.githubusercontent.com/Selalubersamanya7789/signedobson/main/p1cov5/png/skin112.png"
    },
    {
      "id": 113,
      "name_skin": "Pico Skin",
      "install_skin": "https://raw.githubusercontent.com/Selalubersamanya7789/signedobson/main/p1cov5/png/skin113.png"
    },
    {
      "id": 114,
      "name_skin": "Pico Skin",
      "install_skin": "https://raw.githubusercontent.com/Selalubersamanya7789/signedobson/main/p1cov5/png/skin114.png"
    },
    {
      "id": 115,
      "name_skin": "Pico Skin",
      "install_skin": "https://raw.githubusercontent.com/Selalubersamanya7789/signedobson/main/p1cov5/png/skin115.png"
    },
    {
      "id": 116,
      "name_skin": "Pico Skin",
      "install_skin": "https://raw.githubusercontent.com/Selalubersamanya7789/signedobson/main/p1cov5/png/skin116.png"
    },
    {
      "id": 117,
      "name_skin": "Pico Skin",
      "install_skin": "https://raw.githubusercontent.com/Selalubersamanya7789/signedobson/main/p1cov5/png/skin117.png"
    },
    {
      "id": 118,
      "name_skin": "Pico Skin",
      "install_skin": "https://raw.githubusercontent.com/Selalubersamanya7789/signedobson/main/p1cov5/png/skin118.png"
    },
    {
      "id": 119,
      "name_skin": "Pico Skin",
      "install_skin": "https://raw.githubusercontent.com/Selalubersamanya7789/signedobson/main/p1cov5/png/skin119.png"
    },
    {
      "id": 120,
      "name_skin": "Pico Skin",
      "install_skin": "https://raw.githubusercontent.com/Selalubersamanya7789/signedobson/main/p1cov5/png/skin120.png"
    },
    {
      "id": 121,
      "name_skin": "Pico Skin",
      "install_skin": "https://raw.githubusercontent.com/Selalubersamanya7789/signedobson/main/p1cov5/png/skin121.png"
    },
    {
      "id": 122,
      "name_skin": "Pico Skin",
      "install_skin": "https://raw.githubusercontent.com/Selalubersamanya7789/signedobson/main/p1cov5/png/skin122.png"
    },
    {
      "id": 123,
      "name_skin": "Pico Skin",
      "install_skin": "https://raw.githubusercontent.com/Selalubersamanya7789/signedobson/main/p1cov5/png/skin123.png"
    },
    {
      "id": 124,
      "name_skin": "Pico Skin",
      "install_skin": "https://raw.githubusercontent.com/Selalubersamanya7789/signedobson/main/p1cov5/png/skin124.png"
    },
    {
      "id": 125,
      "name_skin": "Pico Skin",
      "install_skin": "https://raw.githubusercontent.com/Selalubersamanya7789/signedobson/main/p1cov5/png/skin125.png"
    },
    {
      "id": 126,
      "name_skin": "Pico Skin",
      "install_skin": "https://raw.githubusercontent.com/Selalubersamanya7789/signedobson/main/p1cov5/png/skin126.png"
    },
    {
      "id": 127,
      "name_skin": "Pico Skin",
      "install_skin": "https://raw.githubusercontent.com/Selalubersamanya7789/signedobson/main/p1cov5/png/skin127.png"
    },
    {
      "id": 128,
      "name_skin": "Pico Skin",
      "install_skin": "https://raw.githubusercontent.com/Selalubersamanya7789/signedobson/main/p1cov5/png/skin128.png"
    },
    {
      "id": 129,
      "name_skin": "Pico Skin",
      "install_skin": "https://raw.githubusercontent.com/Selalubersamanya7789/signedobson/main/p1cov5/png/skin129.png"
    },
    {
      "id": 130,
      "name_skin": "Pico Skin",
      "install_skin": "https://raw.githubusercontent.com/Selalubersamanya7789/signedobson/main/p1cov5/png/skin130.png"
    },
    {
      "id": 131,
      "name_skin": "Pico Skin",
      "install_skin": "https://raw.githubusercontent.com/Selalubersamanya7789/signedobson/main/p1cov5/png/skin131.png"
    },
    {
      "id": 132,
      "name_skin": "Pico Skin",
      "install_skin": "https://raw.githubusercontent.com/Selalubersamanya7789/signedobson/main/p1cov5/png/skin132.png"
    },
    {
      "id": 133,
      "name_skin": "Pico Skin",
      "install_skin": "https://raw.githubusercontent.com/Selalubersamanya7789/signedobson/main/p1cov5/png/skin133.png"
    },
    {
      "id": 134,
      "name_skin": "Pico Skin",
      "install_skin": "https://raw.githubusercontent.com/Selalubersamanya7789/signedobson/main/p1cov5/png/skin134.png"
    }
  ]
}